LICENSE
MANIFEST.in
README.md
pyproject.toml
setup.py
tfds_aihub/__init__.py
tfds_aihub.egg-info/PKG-INFO
tfds_aihub.egg-info/SOURCES.txt
tfds_aihub.egg-info/dependency_links.txt
tfds_aihub.egg-info/requires.txt
tfds_aihub.egg-info/top_level.txt
tfds_aihub/k_fashion_image/__init__.py
tfds_aihub/k_fashion_image/k_fashion_image.py