Metadata-Version: 2.1
Name: tfds-aihub
Version: 0.1.0
Summary: AIHub 데이터를 TFRecord 방식으로 가공하기 위한 프로젝트
Home-page: https://github.com/jeongukjae/tfds-aihub
Author: Ukjae Jeong
Author-email: jeongukjae@gmail.com
License: UNKNOWN
Keywords: tensorflow,machine learning,dataset
Platform: UNKNOWN
Classifier: Development Status :: 3 - Alpha
Classifier: Intended Audience :: Developers
Classifier: Intended Audience :: Science/Research
Classifier: License :: OSI Approved :: Apache Software License
Classifier: Programming Language :: Python :: 3
Classifier: Programming Language :: Python :: 3 :: Only
Classifier: Topic :: Scientific/Engineering :: Artificial Intelligence
Requires-Python: >=3.6
License-File: LICENSE
